{
  "tenants": [
    {
      "nombre": "Ana Gómez",
      "cuarto": "4-K",
      "telefono": "88888888",
      "cedula": "123456789",
      "id": 1
    },
    {
      "nombre": "Carlos Méndez",
      "cuarto": "3-A",
      "telefono": "88776655",
      "cedula": "205460987",
      "id": 2
    },
    {
      "nombre": "Lucía Rojas",
      "cuarto": "2-B",
      "telefono": "89997777",
      "cedula": "302560991",
      "id": 3
    },
    {
      "nombre": "José Ramírez",
      "cuarto": "1-D",
      "telefono": "88112233",
      "cedula": "104780231",
      "id": 4
    },
    {
      "nombre": "María Torres",
      "cuarto": "5-F",
      "telefono": "83224455",
      "cedula": "601890276",
      "id": 5
    },
    {
      "nombre": "Pedro Vargas",
      "cuarto": "3-C",
      "telefono": "89776655",
      "cedula": "502140987",
      "id": 6
    },
    {
      "nombre": "Daniela Castillo",
      "cuarto": "4-J",
      "telefono": "88889999",
      "cedula": "401670423",
      "id": 7
    },
    {
      "nombre": "Sofía Hernández",
      "cuarto": "2-F",
      "telefono": "88665544",
      "cedula": "207540230",
      "id": 8
    },
    {
      "nombre": "Miguel Mora",
      "cuarto": "1-B",
      "telefono": "88773344",
      "cedula": "119770912",
      "id": 9
    },
    {
      "nombre": "Elena Campos",
      "cuarto": "5-A",
      "telefono": "88990022",
      "cedula": "117880945",
      "id": 10
    },
    {
      "id": 11,
      "nombre": "Nick Gurr",
      "cuarto": "4-B",
      "telefono": "12345678",
      "cedula": "123456789"
    },
    {
      "id": 12,
      "nombre": "Orion",
      "cuarto": "5-F",
      "telefono": "11112222",
      "cedula": "123434552"
    }
  ],
  "payments": [
    {
      "cuarto": "4-K",
      "monto": 380,
      "fecha": "2023-05-01"
    },
    {
      "cuarto": "3-A",
      "monto": 350,
      "fecha": "2023-05-02"
    },
    {
      "cuarto": "2-B",
      "monto": 320,
      "fecha": "2023-05-03"
    },
    {
      "cuarto": "1-D",
      "monto": 310,
      "fecha": "2023-05-01"
    },
    {
      "cuarto": "5-F",
      "monto": 390,
      "fecha": "2023-05-02"
    },
    {
      "cuarto": "3-C",
      "monto": 360,
      "fecha": "2023-05-05"
    },
    {
      "cuarto": "4-J",
      "monto": 380,
      "fecha": "2023-05-04"
    },
    {
      "cuarto": "2-F",
      "monto": 330,
      "fecha": "2023-05-06"
    },
    {
      "cuarto": "1-B",
      "monto": 310,
      "fecha": "2023-05-07"
    },
    {
      "cuarto": "5-A",
      "monto": 400,
      "fecha": "2023-05-08"
    },
    {
      "cuarto": "4-B",
      "monto": 370,
      "fecha": "2023-05-10"
    },
    {
      "cuarto": "5-F",
      "monto": 390,
      "fecha": "2023-05-11"
    }
  ],
  "reports": []
}